odoo/addons/l10n_es_ticketbai/README.rst
odoo/addons/l10n_es_ticketbai/__init__.py
odoo/addons/l10n_es_ticketbai/__manifest__.py
odoo/addons/l10n_es_ticketbai/hooks.py
odoo/addons/l10n_es_ticketbai/data/account_fiscal_position_template.xml
odoo/addons/l10n_es_ticketbai/data/tax_map_data.xml
odoo/addons/l10n_es_ticketbai/data/vat_exemption_key_data.xml
odoo/addons/l10n_es_ticketbai/data/vat_regime_key_data.xml
odoo/addons/l10n_es_ticketbai/i18n/es.po
odoo/addons/l10n_es_ticketbai/i18n/l10n_es_ticketbai.pot
odoo/addons/l10n_es_ticketbai/migrations/13.0.1.0.2/post-migration.py
odoo/addons/l10n_es_ticketbai/migrations/13.0.1.2.0/post-migrate.py
odoo/addons/l10n_es_ticketbai/models/__init__.py
odoo/addons/l10n_es_ticketbai/models/account_fiscal_position.py
odoo/addons/l10n_es_ticketbai/models/account_journal.py
odoo/addons/l10n_es_ticketbai/models/account_move.py
odoo/addons/l10n_es_ticketbai/models/account_tax.py
odoo/addons/l10n_es_ticketbai/models/aeat_certificate.py
odoo/addons/l10n_es_ticketbai/models/chart_template.py
odoo/addons/l10n_es_ticketbai/models/ir_sequence.py
odoo/addons/l10n_es_ticketbai/models/res_company.py
odoo/addons/l10n_es_ticketbai/models/ticketbai_invoice.py
odoo/addons/l10n_es_ticketbai/models/ticketbai_tax_map.py
odoo/addons/l10n_es_ticketbai/models/ticketbai_vat_exemption_key.py
odoo/addons/l10n_es_ticketbai/models/ticketbai_vat_regime_key.py
odoo/addons/l10n_es_ticketbai/readme/CONFIGURE.rst
odoo/addons/l10n_es_ticketbai/readme/CONTRIBUTORS.rst
odoo/addons/l10n_es_ticketbai/readme/DESCRIPTION.rst
odoo/addons/l10n_es_ticketbai/readme/USAGE.rst
odoo/addons/l10n_es_ticketbai/security/ir.model.access.csv
odoo/addons/l10n_es_ticketbai/static/description/icon.png
odoo/addons/l10n_es_ticketbai/static/description/index.html
odoo/addons/l10n_es_ticketbai/tests/__init__.py
odoo/addons/l10n_es_ticketbai/tests/common.py
odoo/addons/l10n_es_ticketbai/tests/test_l10n_es_ticketbai_customer_cancellation.py
odoo13_addon_l10n_es_ticketbai-13.0.1.10.5.dist-info/METADATA
odoo13_addon_l10n_es_ticketbai-13.0.1.10.5.dist-info/WHEEL
odoo13_addon_l10n_es_ticketbai-13.0.1.10.5.dist-info/top_level.txt
odoo13_addon_l10n_es_ticketbai-13.0.1.10.5.dist-info/RECORD
